audioperm/__init__.py
audioperm/audioperm.py
audioperm/augmentation.py
audioperm/utils.py
audioperm-0.0.5.dist-info/LICENSE
audioperm-0.0.5.dist-info/METADATA
audioperm-0.0.5.dist-info/WHEEL
audioperm-0.0.5.dist-info/top_level.txt
audioperm-0.0.5.dist-info/RECORD
