Metadata-Version: 2.1
Name: audioperm
Version: 0.0.5
Summary: Audioperm, a python library for generating different permutations of audible segments from audio files.
Home-page: https://github.com/zabir-nabil/audioperm
Author: Zabir Al Nazi
Author-email: zabiralnazi@yahoo.com
License: MIT
Platform: UNKNOWN
Classifier: License :: OSI Approved :: MIT License
Classifier: Programming Language :: Python :: 3
Classifier: Programming Language :: Python :: 3.8
Requires-Dist: feedparser
Requires-Dist: html2text
Requires-Dist: numpy
Requires-Dist: librosa (>=0.8.1)
Requires-Dist: pydub
Requires-Dist: PySoundFile
